da4ml/__init__.py
da4ml/_version.py
da4ml/_binary/__init__.py
da4ml/_binary/dais_bin.cpython-311-x86_64-linux-gnu.so
da4ml/_binary/dais_bin.pyi
da4ml/_cli/__init__.py
da4ml/_cli/convert.py
da4ml/_cli/report.py
da4ml/cmvm/__init__.py
da4ml/cmvm/api.py
da4ml/cmvm/types.py
da4ml/cmvm/core/__init__.py
da4ml/cmvm/core/indexers.py
da4ml/cmvm/core/state_opr.py
da4ml/cmvm/util/__init__.py
da4ml/cmvm/util/bit_decompose.py
da4ml/cmvm/util/mat_decompose.py
da4ml/codegen/__init__.py
da4ml/codegen/hls/__init__.py
da4ml/codegen/hls/hls_codegen.py
da4ml/codegen/hls/hls_model.py
da4ml/codegen/hls/source/binder_util.hh
da4ml/codegen/hls/source/build_binder.mk
da4ml/codegen/hls/source/vitis_bitshift.hh
da4ml/codegen/hls/source/ap_types/ap_binary.h
da4ml/codegen/hls/source/ap_types/ap_common.h
da4ml/codegen/hls/source/ap_types/ap_decl.h
da4ml/codegen/hls/source/ap_types/ap_fixed.h
da4ml/codegen/hls/source/ap_types/ap_fixed_base.h
da4ml/codegen/hls/source/ap_types/ap_fixed_ref.h
da4ml/codegen/hls/source/ap_types/ap_fixed_special.h
da4ml/codegen/hls/source/ap_types/ap_int.h
da4ml/codegen/hls/source/ap_types/ap_int_base.h
da4ml/codegen/hls/source/ap_types/ap_int_ref.h
da4ml/codegen/hls/source/ap_types/ap_int_special.h
da4ml/codegen/hls/source/ap_types/ap_shift_reg.h
da4ml/codegen/hls/source/ap_types/hls_math.h
da4ml/codegen/hls/source/ap_types/hls_stream.h
da4ml/codegen/hls/source/ap_types/etc/ap_private.h
da4ml/codegen/hls/source/ap_types/utils/x_hls_utils.h
da4ml/codegen/rtl/__init__.py
da4ml/codegen/rtl/rtl_model.py
da4ml/codegen/rtl/common_source/binder_util.hh
da4ml/codegen/rtl/common_source/build_binder.mk
da4ml/codegen/rtl/common_source/build_quartus_prj.tcl
da4ml/codegen/rtl/common_source/build_vivado_prj.tcl
da4ml/codegen/rtl/common_source/ioutil.hh
da4ml/codegen/rtl/common_source/template.sdc
da4ml/codegen/rtl/common_source/template.xdc
da4ml/codegen/rtl/verilog/__init__.py
da4ml/codegen/rtl/verilog/comb.py
da4ml-0.5.2.dist-info/METADATA
da4ml-0.5.2.dist-info/WHEEL
da4ml-0.5.2.dist-info/entry_points.txt
da4ml-0.5.2.dist-info/RECORD
da4ml-0.5.2.dist-info/sboms/auditwheel.cdx.json
